setup.py
zipaccess.py
zipaccess.egg-info/PKG-INFO
zipaccess.egg-info/SOURCES.txt
zipaccess.egg-info/dependency_links.txt
zipaccess.egg-info/namespace_packages.txt
zipaccess.egg-info/requires.txt
zipaccess.egg-info/top_level.txt
zipaccess.egg-info/zip-safe