Metadata-Version: 1.0
Name: zipaccess
Version: 0.1rc1
Summary: Access files inside zip archives using standard file functions.
Home-page: https://github.com/iki/zipaccess
Author: Jan Killian
Author-email: jan.killian@gmail.com
License: BSD
Keywords: zip,file,access
Platform: any
Classifier: Development Status :: 4 - Beta
Classifier: Intended Audience :: Developers
Classifier: License :: OSI Approved :: BSD License
Classifier: Operating System :: OS Independent
Classifier: Programming Language :: Python
Classifier: Topic :: Software Development :: Libraries :: Python Modules
